MANIFEST.in
setup.cfg
setup.py
html/angka123
html/coba
html/fix_next_links_url.py
html/pegon_suratman
html/rumah+sakit
html/rumah+sakit2
html/rumah+sakit3
html/rumah+sakit4
html/rumah+sakit5
html/rumah+sakit6
html/rumah+sakit7
html/rumah+sakit8
html/rumah+sakit9
qaamus/__init__.py
qaamus/__main__.py
qaamus/api.py
qaamus/cli.py
qaamus/controller.py
qaamus/default_template
qaamus/out.py
qaamus/parsers.py
qaamus/qaamus.py
qaamus/router.py
qaamus/utils.py
qaamus/view.py
qaamus.egg-info/PKG-INFO
qaamus.egg-info/SOURCES.txt
qaamus.egg-info/dependency_links.txt
qaamus.egg-info/entry_points.txt
qaamus.egg-info/not-zip-safe
qaamus.egg-info/requires.txt
qaamus.egg-info/top_level.txt