Metadata-Version: 1.0
Name: qaamus
Version: 2.0.1
Summary: qaamus, penterjemah indonesia arab. Melalui web qaamus.com 
Home-page: https://github.com/ihfazhillah/qaamus-python
Author: IbnuAmin
Author-email: mihfazhillah@gmail.com
License: MIT
Keywords: qaamus,terjemah,kamus,indonesia arab
Platform: UNKNOWN
